{
   "weather_details": {
      "06-11-2024": {
         "rainfall": 0,
         "t_max": 33,
         "t_min": 22,
         "rh_max": 87,
         "rh_min": 42,
         "wind_speed": 2,
         "wind_direction": 162,
         "cloud_cover": 4
      },
      "07-11-2024": {
         "rainfall": 0,
         "t_max": 33,
         "t_min": 21,
         "rh_max": 91,
         "rh_min": 44,
         "wind_speed": 2,
         "wind_direction": 127,
         "cloud_cover": 3
      },
      "08-11-2024": {
         "rainfall": 0,
         "t_max": 32,
         "t_min": 21,
         "rh_max": 91,
         "rh_min": 46,
         "wind_speed": 2,
         "wind_direction": 121,
         "cloud_cover": 3
      },
      "09-11-2024": {
         "rainfall": 0,
         "t_max": 32,
         "t_min": 21,
         "rh_max": 91,
         "rh_min": 46,
         "wind_speed": 2,
         "wind_direction": 129,
         "cloud_cover": 2
      },
      "10-11-2024": {
         "rainfall": 0,
         "t_max": 32,
         "t_min": 20,
         "rh_max": 90,
         "rh_min": 40,
         "wind_speed": 3,
         "wind_direction": 124,
         "cloud_cover": 3
      }
   },
   "names_of_crops": [
      "ଚାଉଳ",
      "କପା",
      "ଓକ୍ରା",
      "ଆମ୍ବ"
   ],
   "general_advisory": "ଆଗାମୀ ଦିନରେ ପାଗ ଶୁଖିଲା ରହିବ ବୋଲି ଆଶା କରାଯାଉଛି, ତେଣୁ କୃଷକମାନଙ୍କୁ ସେହି ସମଯ଼ରେ କୃଷି କାର୍ଯ୍ଯ଼ କରିବାକୁ ପରାମର୍ଶ ଦିଆଯାଇଛି। ବିଭିନ୍ନ ଫସଲ ପାଇଁ ଉପଯୁକ୍ତ ଜଳସେଚନ ବ୍ଯ଼ବସ୍ଥା କରାଯିବା ଉଚିତ। ପଶୁମାନଙ୍କୁ ଉପଯୁକ୍ତ ଖାଦ୍ଯ଼ ପାଇବା ପାଇଁ ସବୁଜ ପଶୁଖାଦ୍ଯ଼ ବୁଣିବା ପାଇଁ ପରାମର୍ଶ ଦିଆଯିବା ଉଚିତ। ଜଳସେଚନ ସୁବିଧା ଉପଲବ୍ଧ ଥିବା ସ୍ଥାନରେ କୃଷକମାନେ କୋଇଲା ଫସଲ ବୁଣିବା ଏବଂ ରୋପଣ କରିବା ଆରମ୍ଭ କରିବା ଉଚିତ। ପଶୁମାନଙ୍କୁ ପାଦ ଏବଂ ମୁଖ ରୋଗ ଏବଂ ବ୍ରୁସେଲୋସିସ୍ ବିରୁଦ୍ଧରେ କୃମି ଦୂରୀକରଣ ଏବଂ ଟୀକାକରଣ ପରାମର୍ଶ ଦିଆଯିବା ଉଚିତ।",
   "crops_data": {
      "rice": {
         "advisory": [
            "ଆଗାମୀ ଦିନରେ ବର୍ଷା ହେବାର ସମ୍ଭାବନା ବହୁତ କମ୍ ଥିବାରୁ କୃଷକମାନେ ଗୋଟିଏ ଜଳସେଚନ କରି ଧାନ କ୍ଷେତରେ ପର୍ଯ୍ଯ଼ାପ୍ତ ଆର୍ଦ୍ରତା ବଜାଯ଼ ରଖିବା ଉଚିତ।",
            "ବ୍ରାଉନ୍ ପ୍ଲାଣ୍ଟ ହପର (ବିପିଏଚ) କୁ ନିଯ଼ନ୍ତ୍ରଣ କରିବା ପାଇଁ ଟ୍ରାଇଫ୍ଲୁମେଜୋପାଇରିମ୍ 10 ପ୍ରତିଶତ ଏସ୍ସି @94 ମିଲି/ଏକର କିମ୍ବା ପାଇମେଟ୍ରୋଜିନ୍ 50 ପ୍ରତିଶତ ଡବ୍ଲୁଜି @120 ଗ୍ରାମ୍/ଏକର କିମ୍ବା ଡାଇନୋଟେଫୁରାନ୍ 20 ପ୍ରତିଶତ ଏସ୍ଜି @80 ଗ୍ରାମ୍/ଏକର କିମ୍ବା ଇମିଡାକ୍ଲୋପ୍ରିଡ୍ 17.8% ଏସ୍ଏଲ @50 ମିଲି/ଏକର କିମ୍ବା ଫ୍ଲୋନିକାମିଡ୍ 50 ପ୍ରତିଶତ ଡବ୍ଲୁଜି 60 ଗ୍ରାମ୍/ଏକର ସ୍ପ୍ରେ କରନ୍ତୁ।"
         ]
      },
      "cotton": {
         "advisory": [
            "କପା ଫସଲରେ ବୋଲୱର୍ମ କମ୍ପ୍ଲେକ୍ସକୁ ନିଯ଼ନ୍ତ୍ରଣ କରିବା ପାଇଁ, କୃଷକମାନଙ୍କୁ ସ୍ୱଚ୍ଛ ପାଗରେ 10 ଲିଟର ପାଣିରେ 5 ପ୍ରତିଶତ ଏସ୍ଜି @4ଜି କିମ୍ବା ପ୍ରୋଫେନୋଫସ୍ 50 ପ୍ରତିଶତ ଇସି @30 ମିଲି ସିଞ୍ଚନ କରିବାକୁ ପରାମର୍ଶ ଦିଆଯାଇଛି।"
         ]
      },
      "okra": {
         "advisory": [
            "ଓକ୍ରା ଆଦିରେ ଫଳ ଏବଂ ଅଙ୍କୁର ଛେଦକକୁ ନିୟନ୍ତ୍ରଣ କରିବା ପାଇଁ ପ୍ରାରମ୍ଭିକ ପର୍ଯ୍ୟାୟରେ ଏକର ପିଛା ନିମ୍ବ ଆଧାରିତ କୀଟନାଶକ 1500 ପିପିଏମ @600ml ସିଞ୍ଚନ କରିବାକୁ ପରାମର୍ଶ ଦିଆଯିବା ଉଚିତ। ଗୁରୁତର କ୍ଷେତ୍ରରେ, 15 ଦିନର ବ୍ୟବଧାନରେ ଏକର ପିଛା ସ୍ପିନୋସାଦ୍ 45 ପ୍ରତିଶତ ଏସ୍. ସି. @70 ମିଲି ଏବଂ ଇମାମେକ୍ଟିନ୍ ବେନ୍ଜୋଏଟ୍ @80 ଗ୍ରାମ୍ ବିକଳ୍ପ ସ୍ପ୍ରେ କରିବା ପାଇଁ ପରାମର୍ଶ ଦିଆଯିବା ଉଚିତ।",
            "ଫୁଲ ଫୁଟିବା ସମଯ଼ରେ କୃଷକମାନେ କୌଣସି ରାସାଯ଼ନିକ କୀଟନାଶକ ସିଞ୍ଚନ କରିବା ଉଚିତ ନୁହେଁ।"
         ]
      },
      "mango": {
         "advisory": [
            "ପୁରୁଣା ଆମ୍ବ ବଗିଚାରେ, ଆଗାଛା, ରୋଗାକ୍ରାନ୍ତ ଏବଂ ସଂକ୍ରମିତ ଶାଖା ଏବଂ ପତ୍ରର ପ୍ରଶିକ୍ଷଣ, ଛାଣିବା ଏବଂ ସଫା କରିବା ପାଇଁ ପରାମର୍ଶ ଦିଆଯିବା ଉଚିତ। ଯଦି ପତ୍ର ୱେବର୍ ସଂକ୍ରମଣ ହୁଏ, ତେବେ କ୍ୱିନାଲ୍ଫସ୍ 20 ଇ. ସି. ଲିଟର ପିଛା 2.5 ମିଲି. ରେ ସ୍ପ୍ରେ କରିବାକୁ ପରାମର୍ଶ ଦିଆଯିବା ଉଚିତ।",
            "ନୂତନ ଭାବରେ ରୋପଣ କରାଯାଇଥିବା ଆମ୍ବ ବଗିଚାରେ, ଯଦି ପତ୍ର କାଟିବା ଦ୍ୱାରା କୀଟ ଆକ୍ରମଣ ହୁଏ, ତେବେ କୃଷକମାନେ ଏହି କୀଟକୁ ନିୟନ୍ତ୍ରଣ କରିବା ପାଇଁ ଲାମ୍ବଡା ସାଇହାଲୋଥ୍ରିନ୍ 5 ପ୍ରତିଶତ ଇସି ଲିଟର ପିଛା 0.5-1 ମିଲି କିମ୍ବା କ୍ଲୋରୋପାଇରିଫୋସ୍ 20 ଇସି ଲିଟର ପିଛା 2 ମିଲି କିମ୍ବା ସ୍ପିନୋସାଡ୍ 45 ପ୍ରତିଶତ ଏସସି ଲିଟର ପିଛା 0.4 ମିଲି କିମ୍ବା କ୍ୱିନାଲଫୋସ୍ 20 ଇସି ଲିଟର ପିଛା 2 ମିଲି ସ୍ପ୍ରେ କରିବା ଉଚିତ୍।"
         ]
      }
   },
   "date": "05-11-2024"
}