{
   "weather_details": {
      "28.01.2025": {
         "rainfall": 0,
         "t_max": 26,
         "t_min": 14,
         "rh_max": 92,
         "rh_min": 45,
         "wind_speed": 10,
         "wind_direction": 120,
         "cloud_cover": 4
      }
   },
   "names_of_crops": [
      "ଚିନାବାଦାମ",
      "ଆଖୁ",
      "କଦଳୀ",
      "ଫୁଲକୋବି",
      "ଟମାଟୋ",
      "ଆଳୁ",
      "ବାଇଗଣ",
      "କୁକୁଡ଼ା ମାଂସ"
   ],
   "general_advisory": "ଫସଲରେ କୀଟପତଙ୍ଗର ସଂକ୍ରମଣ ପାଇଁ ପାଣିପାଗ ସ୍ଥିତି ଉପଯୁକ୍ତ | ଉତ୍ତମ କୃଷି ଉତ୍ପାଦନ ପାଇଁ ଉପଯୁକ୍ତ କୀଟ ନିୟନ୍ତ୍ରଣ ପଦକ୍ଷେପ ସୁନିଶ୍ଚିତ କରିବା ଏବଂ ସୁପାରିସ କରାଯାଇଥିବା ଅଭ୍ୟାସ ଅନୁସରଣ କରିବା।",
   "crops_data": {
      "groundnut": {
         "advisory": [
            "ଟିକ୍କା ରୋଗ ନିୟନ୍ତ୍ରଣ ପାଇଁ କ୍ଲୋରୋଥାଲୋନିଲ୍ 75 ପ୍ରତିଶତ ଡବ୍ଲ୍ୟୁ. ପି. (ଇଶାନ୍/କାଭାଚ୍) @400 ଗ୍ରାମ୍/ଏକର"
         ]
      },
      "sugarcane": {
         "advisory": [
            "ଗର୍ତ୍ତରେ ରୋପଣ କରିବା ସମୟରେ 87 କିଲୋଗ୍ରାମ ଡିଏପି, 20 କିଲୋଗ୍ରାମ ଏମଓପି ଏବଂ 4 ଟନ ଏଫ୍. ଆଇ. ଏମ୍. ପ୍ରୟୋଗ କରନ୍ତୁ।"
         ]
      },
      "cabbage": {
         "advisory": [
            "ଡିମଣ୍ଡ ବ୍ୟାକ୍ ମଥ୍ ଏବଂ ହେଡ୍ ବୋରର୍ ନିୟନ୍ତ୍ରଣ ପାଇଁ କ୍ୟାଟର୍ପିଲାର୍ ଏବଂ ଅଣ୍ଡା ପିଣ୍ଡ ସଂଗ୍ରହ ଏବଂ ନଷ୍ଟ କରନ୍ତୁ |",
            "ନିମ୍ବ ଆଧାରିତ କୀଟନାଶକ (ଆଜାଦିରାକ୍ଟିନ) 300 ପିପିଏମ ପ୍ରତି ଏକର ପିଛା 1 ଲିଟରରେ ସ୍ପ୍ରେ କରନ୍ତୁ।"
         ]
      },
      "cauliflower": {
         "advisory": [
            "ଡିମଣ୍ଡ ବ୍ୟାକ୍ ମଥ୍ ଏବଂ ହେଡ୍ ବୋରର୍ ନିୟନ୍ତ୍ରଣ ପାଇଁ କ୍ୟାଟର୍ପିଲାର୍ ଏବଂ ଅଣ୍ଡା ପିଣ୍ଡ ସଂଗ୍ରହ ଏବଂ ନଷ୍ଟ କରନ୍ତୁ |",
            "ନିମ୍ବ ଆଧାରିତ କୀଟନାଶକ (ଆଜାଦିରାକ୍ଟିନ) 300 ପିପିଏମ ପ୍ରତି ଏକର ପିଛା 1 ଲିଟରରେ ସ୍ପ୍ରେ କରନ୍ତୁ।"
         ]
      },
      "tomato": {
         "advisory": [
            "ଏଫିଡ୍ ନିୟନ୍ତ୍ରଣ ପାଇଁ ନିମ୍ବ ତେଲ ଗଠନ ବ୍ୟବହାର କରନ୍ତୁ",
            "ପ୍ରଚଳିତ କୁହୁଡ଼ି ଅବସ୍ଥା ଏଫିଡ୍ସର ସଂକ୍ରମଣ ବୃଦ୍ଧି କରିପାରେ |"
         ]
      },
      "potato": {
         "advisory": [
            "ପ୍ରାରମ୍ଭିକ ବ୍ଲାଇଟ୍ ରୋଗ ନିୟନ୍ତ୍ରଣ ପାଇଁ ମାନକୋଜେବ୍ 75% ଡବ୍ଲ୍ୟୁ. ପି. @600 ଗ୍ରାମ୍/ଏକର ସ୍ପ୍ରେ କରନ୍ତୁ।"
         ]
      },
      "brinjal": {
         "advisory": [
            "ଏପିଲାକ୍ନା ବିଟଲ ନିୟନ୍ତ୍ରଣ ପାଇଁ ଗ୍ରବ୍, ପିଉପା ଏବଂ ବୟସ୍କମାନଙ୍କୁ ହଟାଇବା ପାଇଁ ଗଛଗୁଡ଼ିକୁ ହଲାନ୍ତୁ",
            "ନିମ୍ବ-ଆଧାରିତ କୀଟନାଶକ (ଆଜାଦିରାକ୍ଟିନ) 1500 ପିପିଏମ @3 ମିଲି/ଲିଟର ପାଣି ସ୍ପ୍ରେ କରନ୍ତୁ।"
         ]
      },
      "poultry": {
         "advisory": [
            "ଶୋଇବା ରୋଗ ନିୟନ୍ତ୍ରଣ ପାଇଁ 7 ଦିନରେ ଲାସୋଟା ଏବଂ 13-15 ଦିନ ମଧ୍ୟରେ IBD ଟିକା ସହିତ ଛୁଆମାନଙ୍କୁ ଟୀକାକରଣ କରନ୍ତୁ।"
         ]
      }
   },
   "date": "28-01-2025"
}