{
   "weather_details": {
      "11/01/2025": {
         "rainfall": 0,
         "t_max": 27,
         "t_min": 15,
         "rh_max": 84,
         "rh_min": 39,
         "wind_speed": 5,
         "wind_direction": 297,
         "cloud_cover": 0
      },
      "18/01/2025": {
         "rainfall": 0,
         "t_max": 25,
         "t_min": 15,
         "rh_max": 84,
         "rh_min": 39,
         "wind_speed": 5,
         "wind_direction": 297,
         "cloud_cover": 0
      },
      "19/01/2025": {
         "rainfall": 0,
         "t_max": 26,
         "t_min": 15,
         "rh_max": 83,
         "rh_min": 42,
         "wind_speed": 6,
         "wind_direction": 325,
         "cloud_cover": 0
      },
      "20/01/2025": {
         "rainfall": 0,
         "t_max": 26,
         "t_min": 15,
         "rh_max": 83,
         "rh_min": 42,
         "wind_speed": 6,
         "wind_direction": 325,
         "cloud_cover": 0
      },
      "21/01/2025": {
         "rainfall": 0,
         "t_max": 27,
         "t_min": 16,
         "rh_max": 83,
         "rh_min": 42,
         "wind_speed": 6,
         "wind_direction": 325,
         "cloud_cover": 0
      }
   },
   "names_of_crops": [
      "ଧାନ।",
      "ଚିନାବାଦାମ",
      "ଆଖୁ",
      "କଦଳୀ",
      "କୋଇଲା ଫସଲ",
      "ନଡ଼ିଆ",
      "କଦଳୀ",
      "ମତ୍ସ୍ୟଚାଷ"
   ],
   "general_advisory": "ବୁଣିବା ପୂର୍ବରୁ ନର୍ସରୀ ଶଯ୍ୟା ପ୍ରସ୍ତୁତ କରିବା ଏବଂ ଧାନ ମଞ୍ଜି ଉପଚାର କରିବା ପାଇଁ କୃଷକମାନଙ୍କୁ ପରାମର୍ଶ ଦିଆଯାଇଛି। ଗାଧୋଇବା ପନିପରିବା ଚାରା ଏବଂ ଫସଲକୁ ହାଲୁକା ଜଳସେଚନ ପ୍ରଦାନ କରେ | ଆଗାଛା ନିୟନ୍ତ୍ରଣ ପାଇଁ ତୃଣନାଶକ ବ୍ୟବହାର କରନ୍ତୁ ଏବଂ ବିଭିନ୍ନ ଫସଲ ପାଇଁ ଉପଯୁକ୍ତ ସାର ପ୍ରୟୋଗ କରନ୍ତୁ।",
   "crops_data": {
      "paddy": {
         "advisory": [
            "ବାସଲ ସାର ପ୍ରୟୋଗଃ ଶେଷ ପୋଖରୀ ସମୟରେ ଏକର ପିଛା ଡିଏପି, ଏମଓପି ଏବଂ ୟୁରିଆ ଲଗାନ୍ତୁ। ଅଧିକ ଉତ୍ପାଦନ ପାଇଁ ଉପଯୁକ୍ତ ବ୍ୟବଧାନରେ 25-30 ଦିନର ପୁରୁଣା ଚାରା ରୋପଣ କରନ୍ତୁ।"
         ]
      },
      "groundnut": {
         "advisory": [
            "ହ୍ୱାଇଟ୍ ଗ୍ରାବ୍ ସଂକ୍ରମଣଃ ଉଦ୍ଭିଦ ତଳେ କ୍ଲୋରୋପାଇରିଫସ୍ କିମ୍ବା ଇମିଡାକ୍ଲୋପ୍ରିଡ୍ ବୁଡ଼ାଇ କମ୍ କରନ୍ତୁ |",
            "ଷ୍ଟେମ ରଟ୍ ନିୟନ୍ତ୍ରଣଃ ଭାଲିଡାମାଇସିନ୍ କିମ୍ବା କ୍ୟାପଟାନ + ହେକ୍ସାକୋନାଜୋଲ ସହିତ ମୃତ୍ତିକାକୁ ଭିଜାଇ ଦିଅନ୍ତୁ |"
         ]
      },
      "sugarcane": {
         "advisory": [
            "ରୋପଣ ପର୍ଯ୍ୟାୟଃ ରୋପଣ ସମୟରେ ଡିଏପି, ଏମଓପି ଏବଂ ଏଫୱାଇଏମ ପ୍ରୟୋଗ କରନ୍ତୁ। ନିର୍ଦ୍ଦିଷ୍ଟ ବ୍ୟବଧାନରେ ୟୁରିଆ ସହିତ ଶୀର୍ଷ ପୋଷାକ | ବିଳମ୍ବରେ ୟୁରିଆ ପ୍ରୟୋଗରୁ ଦୂରେଇ ରୁହନ୍ତୁ।",
            "ଏନ୍/ଏ"
         ]
      },
      "cowpea": {
         "advisory": [
            "କେଶର କ୍ୟାଟର୍ପିଲର ନିୟନ୍ତ୍ରଣଃ ନିୟନ୍ତ୍ରଣ ପାଇଁ ଫ୍ଲୁବେଣ୍ଡିଆମାଇଡ୍ କିମ୍ବା ଡିଫିନୋକୋନାଜୋଲ୍ ସ୍ପ୍ରେ କରନ୍ତୁ।",
            "ଏନ୍/ଏ"
         ]
      },
      "cole crops": {
         "advisory": [
            "ଡିମଣ୍ଡ ବ୍ୟାକ୍ ମଥ୍ ଏବଂ ହେଡ୍ ବୋରର୍ ମ୍ୟାନେଜମେଣ୍ଟଃ କ୍ୟାଟର୍ପିଲାର୍ ସଂଗ୍ରହ କରନ୍ତୁ ଏବଂ ନଷ୍ଟ କରନ୍ତୁ। କୀଟ ନିୟନ୍ତ୍ରଣ ପାଇଁ ନିମ ଆଧାରିତ କୀଟନାଶକ କିମ୍ବା ରାସାୟନିକ ସ୍ପ୍ରେ ପ୍ରୟୋଗ କରନ୍ତୁ।"
         ]
      },
      "coconut": {
         "advisory": [
            "ରେଡ୍ ପାମ୍ ୱିଭିଲ୍ ସଂକ୍ରମଣଃ ନିୟନ୍ତ୍ରଣ ପାଇଁ ଷ୍ଟେମ ଛିଦ୍ରରେ କାର୍ବେନଡାଜିମ୍ ଲଗାନ୍ତୁ |",
            "ଗଣ୍ଡା ଭୃଣ ନିୟନ୍ତ୍ରଣଃ ନିକଟସ୍ଥ କମ୍ପୋଷ୍ଟ ପ୍ରାଙ୍ଗଣକୁ ସଫା ଏବଂ ଜୀବାଣୁମୁକ୍ତ କରନ୍ତୁ।"
         ]
      },
      "banana": {
         "advisory": [
            "ସିଗଟୋକା ଲିଫ୍ ସ୍ପଟ୍ କଣ୍ଟ୍ରୋଲ୍ଃ ଲିଟର ପିଛା କାର୍ବେନଡାଜିମ୍ କିମ୍ବା କ୍ଲୋରୋଥାଲୋନିଲ୍ ସ୍ପ୍ରେ କରନ୍ତୁ।",
            "ଏନ୍/ଏ"
         ]
      },
      "pisciculture": {
         "advisory": [
            "ଇ. ୟୁ. ଏସ୍. ପ୍ରତିରୋଧଃ ପ୍ରତିଷେଧକ ପଦକ୍ଷେପ ସ୍ୱରୂପ ପୋଖରୀ ଅଞ୍ଚଳରେ ପାଣି ସହିତ 'ସିଫ୍ୟାକ୍ସ \"ଲଗାନ୍ତୁ। ପ୍ରତିଦିନ ମାଛମାନଙ୍କୁ ତୈଳ କେକ୍ ବ୍ରାନ୍ ମିଶ୍ରଣ ସହିତ ଖାଇବାକୁ ଦିଅନ୍ତୁ |",
            "ଏନ୍/ଏ"
         ]
      }
   },
   "date": "17-01-2025"
}