{
   "weather_details": {
      "30-10-2024": {
         "rainfall": 6,
         "t_max": 31,
         "t_min": 20,
         "rh_max": 97.8,
         "rh_min": 72,
         "wind_speed": 2,
         "wind_direction": 194,
         "cloud_cover": 7
      },
      "31-10-2024": {
         "rainfall": 2,
         "t_max": 31,
         "t_min": 20,
         "rh_max": 97.6,
         "rh_min": 69,
         "wind_speed": 1,
         "wind_direction": 90,
         "cloud_cover": 6
      },
      "01-11-2024": {
         "rainfall": 0,
         "t_max": 30,
         "t_min": 19,
         "rh_max": 96,
         "rh_min": 59,
         "wind_speed": 1,
         "wind_direction": 198,
         "cloud_cover": 5
      },
      "02-11-2024": {
         "rainfall": 0,
         "t_max": 30,
         "t_min": 19,
         "rh_max": 93.2,
         "rh_min": 57,
         "wind_speed": 1,
         "wind_direction": 153.5,
         "cloud_cover": 5
      },
      "03-11-2024": {
         "rainfall": 0,
         "t_max": 30,
         "t_min": 18,
         "rh_max": 90.7,
         "rh_min": 47,
         "wind_speed": 1,
         "wind_direction": 146.3,
         "cloud_cover": 4
      }
   },
   "names_of_crops": [
      "ଚାଉଳ",
      "ରାଇକିଆ ବିନ୍ସ",
      "ସୁଚିନ୍ତିତ ଲାଉ",
      "ମକା",
      "ସୋରିଷ"
   ],
   "general_advisory": "ପବନର ମନ୍ଥର ବେଗ ଦେଖି କୃଷକମାନେ ରାସାଯ଼ନିକ ପଦାର୍ଥ ଏବଂ କୀଟନାଶକ ସିଞ୍ଚନ ପୁଣି ଆରମ୍ଭ କରିପାରିବେ। ପରିପକ୍ୱ ଫସଲଗୁଡ଼ିକୁ ଅମଳ କରି ତୁରନ୍ତ ନଷ୍ଟ କରିଦିଅନ୍ତୁ। ଫସଲ ପାଣିପାଗ ସମ୍ବନ୍ଧୀଯ଼ ସୂଚନା ପାଇବା ପାଇଁ କୃଷକମାନଙ୍କୁ ସେମାନଙ୍କର ହ୍ୱାଟ୍ସଆପ୍ ଏବଂ ବାର୍ତ୍ତା ଯାଞ୍ଚ କରିବାକୁ ପରାମର୍ଶ ଦିଆଯାଇଛି।",
   "crops_data": {
      "rice": {
         "advisory": [
            "ବୁଟିଂ ପର୍ଯ୍ଯ଼ାଯ଼",
            "ଫୁଲ ଫୁଟିବା ସମଯ଼ରେ କ୍ଷେତକୁ ଜଳସେଚନ କରି ସାର (ପୋଟାସ ଏବଂ ଯ଼ୁରିଆ) ର ଅନ୍ତିମ ମାତ୍ରା ପ୍ରଯ଼ୋଗ କରନ୍ତୁ।"
         ]
      },
      "raikia beans": {
         "advisory": [
            "ପରିପକ୍ୱତା-ଅମଳ",
            "ପରିପକ୍ୱ ବିନ୍ସ ଅମଳ କରନ୍ତୁ ଏବଂ ଏହାକୁ ନିକଟସ୍ଥ ବଜାରରେ ବିକ୍ରଯ଼ କରନ୍ତୁ |"
         ]
      },
      "pointed gourd": {
         "advisory": [
            "କ୍ଷେତରୁ ପରିପକ୍ୱ ଫସଲ ଅମଳ କରନ୍ତୁ।",
            "କ୍ଷେତରେ ପାଣି ଛିଡ଼ା ହୋଇ ରହିଥିବାରୁ ସଂକ୍ରମିତ ହେଲେ କ୍ଷତିଗ୍ରସ୍ତ ଫସଲକୁ ବାହାର କରିଦିଅନ୍ତୁ।",
            "କ୍ଷେତକୁ ସାନିଟାଇଜ କରନ୍ତୁ।"
         ]
      },
      "maize": {
         "advisory": [
            "ପରିପକ୍ୱତା-ଅମଳ",
            "ପରିପକ୍ୱ ଶସ୍ୟଗୁଡ଼ିକୁ ଅମଳ କରନ୍ତୁ।"
         ]
      },
      "mustard": {
         "advisory": [
            "ବୁଣିବା",
            "ଏହାକୁ ସୂକ୍ଷ୍ମ ଚାଷ ମାଟିରେ ପ୍ରସାରଣ କରାଯାଇପାରିବ।",
            "ଏଫ୍. ଆଇ. ଏମ୍. 25 ଟନ୍ ଏବଂ ଏନ୍. 25 କି. ଗ୍ରା., ପି. 60 କି. ଗ୍ରା./ହେକ୍ଟରର ମୂଳ ପ୍ରୟୋଗ।",
            "ZnSO4 @37.5 କି. ଗ୍ରା./ହେକ୍ଟରର Zn ପ୍ରଯ଼ୋଗ ଫଳରେ ଉତ୍ପାଦନ ବୃଦ୍ଧି ପାଇବ।"
         ]
      }
   },
   "date": "29-10-2024",
   "ERROR": "ନିଯ଼ମିତ ତଥ୍ଯ଼ ମିଳୁନାହିଁ।"
}