{
   "weather_details": {
      "29/01/2025": {
         "rainfall": 0,
         "t_max": 31,
         "t_min": 10,
         "rh_max": 64,
         "rh_min": 24,
         "wind_speed": 3,
         "wind_direction": 54,
         "cloud_cover": 1
      },
      "30/01/2025": {
         "rainfall": 0,
         "t_max": 30,
         "t_min": 11,
         "rh_max": 72,
         "rh_min": 27,
         "wind_speed": 2,
         "wind_direction": 76,
         "cloud_cover": 2
      },
      "31/01/2025": {
         "rainfall": 0,
         "t_max": 30,
         "t_min": 12,
         "rh_max": 71,
         "rh_min": 22,
         "wind_speed": 2,
         "wind_direction": 90,
         "cloud_cover": 1
      },
      "01/02/2025": {
         "rainfall": 0,
         "t_max": 31,
         "t_min": 12,
         "rh_max": 62,
         "rh_min": 22,
         "wind_speed": 2,
         "wind_direction": 63,
         "cloud_cover": 1
      },
      "02/02/2025": {
         "rainfall": 0,
         "t_max": 31,
         "t_min": 12,
         "rh_max": 64,
         "rh_min": 21,
         "wind_speed": 3,
         "wind_direction": 0,
         "cloud_cover": 2
      }
   },
   "names_of_crops": [
      "ମଞ୍ଜି ଏବଂ ସୋରିଷ",
      "ରବି ଧାନ",
      "ଗହମ",
      "ଗ୍ରୀଷ୍ମକାଳୀନ ମକା",
      "ସେସମମ୍",
      "ଗ୍ରୀଷ୍ମ ଋତୁର ଚିନାବାଦାମ",
      "ରାଗି।",
      "ପନିପରିବା",
      "ମତ୍ସ୍ୟଚାଷ",
      "କୁକୁଡ଼ା ଚାଷ"
   ],
   "general_advisory": "ଧାନ କ୍ଷେତରେ ହାଲୁକା ଜଳସେଚନ ବ୍ୟବସ୍ଥା କରନ୍ତୁ। ରବି ଫସଲ ପାଇଁ ଗୁରୁତ୍ୱପୂର୍ଣ୍ଣ ଜଳସେଚନ ବ୍ୟବସ୍ଥା ରଖନ୍ତୁ. କୀଟ ଆକ୍ରମଣ ପାଇଁ ସର୍ଭେ କରନ୍ତୁ ଏବଂ ଆବଶ୍ୟକ ପଦକ୍ଷେପ ନିଅନ୍ତୁ। ରବି ଫସଲରେ ସମ୍ପୂର୍ଣ୍ଣ ଜମି। ପାଣିପାଗ କାରଣରୁ ବିଭିନ୍ନ ଫସଲରେ ପାଉଡର ଫଙ୍ଗୁର ହେବାର ସମ୍ଭାବନା ରହିଛି, ଯାହା 200 ଲିଟର ପାଣିରେ 1 କିଲୋଗ୍ରାମ ସ୍ପ୍ରେ ସଲଫର୍ ପାଉଡର ପରିଚାଳନା କରିଥାଏ।",
   "crops_data": {
      "rape seed & mustard": {
         "advisory": [
            "ପାଣିପାଗ କାରଣରୁ ଏଫିଡ୍ସର ଗୁରୁତର ସଂକ୍ରମଣ ହେବ, ଇମିଡାକ୍ଲୋପ୍ରିଡ୍ କିମ୍ବା ଡାଇମେଥୋଏଟ୍ @2 ମିଲି/ଲିଟର ସ୍ପ୍ରେ କରନ୍ତୁ।",
            "ପୁଷ୍ପ ଏବଂ ଶୁଆ ବିକାଶ ପର୍ଯ୍ୟାୟରେ ଗୁରୁତ୍ୱପୂର୍ଣ୍ଣ ପର୍ଯ୍ୟାୟରେ ଗୋଟିଏ ଜଳସେଚନ ପ୍ରଦାନ କରନ୍ତୁ।"
         ]
      },
      "rabi paddy": {
         "advisory": [
            "ଅନ୍ତିମ ଭୂମି ପ୍ରସ୍ତୁତି ପାଇଁ ଯାଆନ୍ତୁ ଏବଂ ଏକର ପିଛା 35-କିଲୋଗ୍ରାମ ଡିଏପି, 20-କିଲୋଗ୍ରାମ ଏମଓପି ଏବଂ 8-କିଲୋଗ୍ରାମ ୟୁରିଆ ପ୍ରୟୋଗ କରନ୍ତୁ। ସାର ପ୍ରୟୋଗର 48 ଘଣ୍ଟା ପରେ ପୁଣି ଜଳସେଚନ ବ୍ୟବସ୍ଥା କରନ୍ତୁ।",
            "25-30 ଦିନ ପୁରୁଣା ଚାରା ରୋପଣ କରାଯିବା ଉଚିତ।"
         ]
      },
      "wheat": {
         "advisory": [
            "ପାଣିପାଗ କାରଣରୁ ଷ୍ଟେମ ବୋରର ଆକ୍ରମଣର ସମ୍ଭାବନା ରହିଛି, ଏହି ସ୍ପ୍ରେକୁ ପରିଚାଳନା କରିବା ପାଇଁ ଟ୍ରାୟାଜୋଫୋସ @2 ମିଲି/ଲିଟର ପାଣି।",
            "ଫସଲକୁ ଗୁରୁତ୍ୱପୂର୍ଣ୍ଣ ପର୍ଯ୍ୟାୟ ଜଳସେଚନ ପ୍ରଦାନ କରନ୍ତୁ।",
            "ଯେକୌଣସି କୀଟ ପାଇଁ ସର୍ଭେ କରନ୍ତୁ।",
            "ଏକର ପିଛା 12-16 କିଲୋଗ୍ରାମ ନାଇଟ୍ରୋଜେନ୍ ଲଗାନ୍ତୁ।"
         ]
      },
      "summer maize": {
         "advisory": [
            "ମକା ବୁଣିବା ପାଇଁ ଏହା ଉପଯୁକ୍ତ ସମୟ।",
            "ମକା ବୁଣିବାରେ ବିଳମ୍ବ ହେଲେ ଉଚ୍ଚ ତାପମାତ୍ରା କାରଣରୁ ପରାଗଣ ବାଧାପ୍ରାପ୍ତ ହେବ।",
            "ବିଳମ୍ବ ନକରି ଏକର ପିଛା 6 କିଲୋଗ୍ରାମ ମକା ବୁଣନ୍ତୁ।",
            "ୱାର୍ମାଇଟ ପ୍ରବଣ ଅଞ୍ଚଳରେ ଏକର ପିଛା 10 କିଲୋଗ୍ରାମ କ୍ଲୋରପିରିଫସ୍ ଲଗାନ୍ତୁ।"
         ]
      },
      "sesamum": {
         "advisory": [
            "ପ୍ରାଚି, ଜି-10, କାଳିକା ଭଳି ତିଲ ପ୍ରତି ଏକର ପିଛା 3 କି. ଗ୍ରା. ରେ ବୁଣିବା ପାଇଁ ଯାଆନ୍ତୁ।",
            "ମୃତ୍ତିକା ଜନ୍ମିତ ଏବଂ ବୀଜ ଜନ୍ମିତ ରୋଗର ସୁରକ୍ଷା ପାଇଁ ମଞ୍ଜିଗୁଡ଼ିକୁ ଚିକିତ୍ସା କରନ୍ତୁ।",
            "ଏକର ପିଛା 12-8 କି. ଗ୍ରା. ଏନ. ପି. କେ. ସହିତ 10 କି. ଗ୍ରା. ଗନ୍ଧକକୁ ମୂଳ ମାତ୍ରା ଭାବେ ପ୍ରୟୋଗ କରନ୍ତୁ।"
         ]
      },
      "summer groundnut": {
         "advisory": [
            "30 x 10 ସେ. ମି. ବ୍ୟବଧାନରେ ଗ୍ରୀଷ୍ମକାଳୀନ ଚିନାବାଦାମ ସମ୍ପୂର୍ଣ୍ଣ ବୁଣିବା।",
            "ବୀଜର ହାର ହେଉଛି 50 କିଲୋଗ୍ରାମ ଶୁଆ/ଏସି।",
            "ପ୍ରାରମ୍ଭିକ ବୁଣାଯାଇଥିବା ଫସଲରେ, ଫୁଲ ଫୁଟିବା ପରେ ପରସ୍ପର ମଧ୍ୟରେ ଚାଷ କରନ୍ତୁ ନାହିଁ।"
         ]
      },
      "ragi": {
         "advisory": [
            "କ୍ଷେତ ପ୍ରସ୍ତୁତ କରନ୍ତୁ ଏବଂ ଅନ୍ତିମ ଜମି ପ୍ରସ୍ତୁତି ସମୟରେ ଏଫ. ୱାଇ. ଏମ୍./ଏସି. ର 2 ଟନ ପ୍ରୟୋଗ କରନ୍ତୁ।",
            "21 ଦିନ ପୁରୁଣା ରାଗି ଚାରା 22.5 x 10 ସେ. ମି. ବ୍ୟବଧାନରେ ରୋପଣ କରନ୍ତୁ।"
         ]
      },
      "vegetable": {
         "advisory": [
            "କାକୁର୍ବୋଟ୍ଗୁଡ଼ିକରେ, ଡାଉନି ମିଲ୍ଡିଉ ହେବାର ସମ୍ଭାବନା ରହିଛି, ଏହାକୁ ନିୟନ୍ତ୍ରଣ କରିବା ପାଇଁ ମାକୋଜେବ୍ @2.5 ଗ୍ରାମ/ଲିଟର ପାଣି ଲଗାନ୍ତୁ।"
         ]
      },
      "fish farming": {
         "advisory": [
            "ଶରୀରର ଓଜନ ଅନୁଯାୟୀ ଖାଦ୍ୟ ମିଶ୍ରଣ ପ୍ରଦାନ କରନ୍ତୁ।"
         ]
      },
      "poultry farming": {
         "advisory": [
            "କୁକୁଡ଼ା ଘର ସଫା ରଖନ୍ତୁ।"
         ]
      }
   },
   "date": "28-01-2025"
}