{
   "weather_details": {
      "27.01.2025": {
         "rainfall": 0,
         "t_max": 32,
         "t_min": 17,
         "rh_max": 81,
         "rh_min": 0,
         "wind_speed": 0,
         "wind_direction": 0,
         "cloud_cover": 0
      },
      "28.01.2025": {
         "rainfall": 0,
         "t_max": 31,
         "t_min": 17,
         "rh_max": 81,
         "rh_min": 0,
         "wind_speed": 0,
         "wind_direction": 0,
         "cloud_cover": 0
      },
      "29.01.2025": {
         "rainfall": 0,
         "t_max": 32,
         "t_min": 17,
         "rh_max": 75,
         "rh_min": 0,
         "wind_speed": 0,
         "wind_direction": 0,
         "cloud_cover": 0
      },
      "30.01.2025": {
         "rainfall": 0,
         "t_max": 31,
         "t_min": 18,
         "rh_max": 72,
         "rh_min": 0,
         "wind_speed": 0,
         "wind_direction": 0,
         "cloud_cover": 0
      },
      "31.01.2025": {
         "rainfall": 0,
         "t_max": 32,
         "t_min": 18,
         "rh_max": 81,
         "rh_min": 63,
         "wind_speed": 2,
         "wind_direction": 117,
         "cloud_cover": 2
      },
      "01.02.2025": {
         "rainfall": 0,
         "t_max": 33,
         "t_min": 18,
         "rh_max": 81,
         "rh_min": 63,
         "wind_speed": 2,
         "wind_direction": 117,
         "cloud_cover": 3
      },
      "02.02.2025": {
         "rainfall": 0,
         "t_max": 34,
         "t_min": 19,
         "rh_max": 75,
         "rh_min": 0,
         "wind_speed": 2,
         "wind_direction": 127,
         "cloud_cover": 3
      },
      "03.02.2025": {
         "rainfall": 0,
         "t_max": 34,
         "t_min": 19,
         "rh_max": 72,
         "rh_min": 0,
         "wind_speed": 3,
         "wind_direction": 106,
         "cloud_cover": 3
      },
      "04.02.2025": {
         "rainfall": 0,
         "t_max": 33,
         "t_min": 18,
         "rh_max": 63,
         "rh_min": 0,
         "wind_speed": 2,
         "wind_direction": 76,
         "cloud_cover": 2
      }
   },
   "names_of_crops": [
      "rice",
      "groundnut",
      "mustard",
      "chilli",
      "tomato",
      "potato",
      "mushroom"
   ],
   "general_advisory": "Farmers are advised to do weeding and hoeing in the standing crops like Maize, Groundnut, Green gram, Chick pea and vegetables to protect them from weeds. Apply balanced and appropriate fertilizers according to crop’s growth stage. Install yellow sticky trap to monitor sucking pest like White fly, Aphids, Jassids & Thirps in vegetables at vegetative stage. Rouging of viral infested plant should be done in vegetables. Use pheromone trap for monitoring borer insect in vegetables like brinjal, cauliflower, cabbage, tomato etc. Tikka: If symptom is noticed, application of Chlorothalonil 75% WP or Hexaconazole 5% EC or Mancozeb 75% WP mixed with water is recommended.",
   "crops_data": {
      "rice": {
         "advisory": [
            "Weed Management: Apply herbicide according to crop growth stage. Pest Management: Install pheromone traps to monitor pest population"
         ]
      },
      "groundnut": {
         "advisory": [
            "Tikka: If symptom is noticed, apply recommended chemicals mixed with water"
         ]
      },
      "mustard": {
         "advisory": [
            "Regularly monitor for pests like grasshopper, aphids, and larvae. Spray recommended chemicals when necessary"
         ]
      },
      "chilli": {
         "advisory": [
            "Provide vermicompost and manures to the crop.",
            "Spray Dimethoate if little leaf is noticed.",
            "Manage aphids and Jassids infestation with recommended chemicals",
            "Apply appropriate chemicals for mite infestation"
         ]
      },
      "tomato": {
         "advisory": [
            "Monitor pest population with yellow sticky traps",
            "Use recommended chemicals for controlling white fly infestation"
         ]
      },
      "potato": {
         "advisory": [
            "Provide irrigation as needed",
            "Earthing up required to prevent direct exposure to sun",
            "Use recommended chemicals for wilting"
         ]
      },
      "mushroom": {
         "advisory": [
            "For Oyster mushroom cultivation use Niger sticks as substrate"
         ]
      }
   },
   "date": "31-01-2025"
}