{
   "weather_details": {
      "03/04/2024": {
         "rainfall": 0,
         "t_max": 40,
         "t_min": 26,
         "rh_max": 57,
         "rh_min": 13,
         "wind_speed": 12,
         "wind_direction": 205,
         "cloud_cover": 0
      },
      "04/04/2024": {
         "rainfall": 0,
         "t_max": 40,
         "t_min": 26,
         "rh_max": 80,
         "rh_min": 15,
         "wind_speed": 11,
         "wind_direction": 180,
         "cloud_cover": 1
      },
      "05/04/2024": {
         "rainfall": 0,
         "t_max": 41,
         "t_min": 27,
         "rh_max": 70,
         "rh_min": 23,
         "wind_speed": 15,
         "wind_direction": 207,
         "cloud_cover": 1
      },
      "06/04/2024": {
         "rainfall": 0,
         "t_max": 41,
         "t_min": 27,
         "rh_max": 67,
         "rh_min": 15,
         "wind_speed": 13,
         "wind_direction": 210,
         "cloud_cover": 0
      },
      "07/04/2024": {
         "rainfall": 0,
         "t_max": 42,
         "t_min": 27,
         "rh_max": 55,
         "rh_min": 10,
         "wind_speed": 12,
         "wind_direction": 242,
         "cloud_cover": 2
      }
   },
   "names_of_crops": [
      "paddy",
      "sugarcane",
      "maize",
      "tomato",
      "brinjal",
      "coconut",
      "vegetables",
      "fingerlings"
   ],
   "general_advisory": "In paddy crop, Panicle initiation, Panicle emergence, flowering and milking stages are critical. Cover rows with dry leaves in Sugarcane. Apply sprinkler irrigation for heat effect reduction. Irrigate maize crop adequately. Spread polythene in irrigation channels for water conservation. Take precautions for high temperatures in tomato and brinjal.",
   "crops_data": {
      "paddy": {
         "advisory": [
            "Yellow stem borer management"
         ]
      },
      "sugarcane": {
         "advisory": [
            "Early Shoot Borer management"
         ]
      },
      "maize": {
         "advisory": [
            "Irrigate the crop adequately"
         ]
      },
      "tomato": {
         "advisory": [
            "Apply 1g Streptocyclin in 10 liter water in root zone for wilting prevention"
         ]
      },
      "brinjal": {
         "advisory": [
            "Brinjal shoot and fruit borer management"
         ]
      },
      "coconut": {
         "advisory": [
            "Mulch coconut leaves 1.8m around a coconut tree for water loss reduction"
         ]
      },
      "vegetables": {
         "advisory": [
            "Cover with paper caps on newly planted vegetable seedlings during day time"
         ]
      },
      "fingerlings": {
         "advisory": [
            "Harvest fingerlings in shallow ponds if water temperature rises to 30°C"
         ]
      }
   },
   "date": "02-04-2024"
}