{
   "weather_details": {
      "21/09/2024": {
         "rainfall": 2,
         "t_max": 33,
         "t_min": 25,
         "rh_max": 87,
         "rh_min": 52,
         "wind_speed": 4,
         "wind_direction": 79,
         "cloud_cover": 4
      },
      "22/09/2024": {
         "rainfall": 4,
         "t_max": 33,
         "t_min": 25,
         "rh_max": 86,
         "rh_min": 54,
         "wind_speed": 5,
         "wind_direction": 112,
         "cloud_cover": 4
      },
      "23/09/2024": {
         "rainfall": 6,
         "t_max": 33,
         "t_min": 25,
         "rh_max": 89,
         "rh_min": 56,
         "wind_speed": 5,
         "wind_direction": 135,
         "cloud_cover": 6
      },
      "24/09/2024": {
         "rainfall": 10,
         "t_max": 34,
         "t_min": 26,
         "rh_max": 92,
         "rh_min": 58,
         "wind_speed": 5,
         "wind_direction": 116,
         "cloud_cover": 7
      },
      "25/09/2024": {
         "rainfall": 10,
         "t_max": 34,
         "t_min": 26,
         "rh_max": 95,
         "rh_min": 57,
         "wind_speed": 8,
         "wind_direction": 108,
         "cloud_cover": 8
      }
   },
   "names_of_crops": [
      "ଧାନ।",
      "ଖରିଫ ଡାଲି",
      "ରାଗି।",
      "ସେସମମ୍",
      "ମକା",
      "ଚିନାବାଦାମ",
      "ଅଦା।",
      "ପନିପରିବା",
      "କାକୁଡ଼ି",
      "ଫୁଲ.",
      "ମତ୍ସ୍ଯ଼ଚାଷ"
   ],
   "general_advisory": "ବହୁତ ହାଲୁକା ରୁ ହାଲୁକା ବର୍ଷା ହେବାର ପୂର୍ବାନୁମାନ ହେତୁ କୃଷକମାନଙ୍କୁ ସାର ଏବଂ ରାସାୟନିକ ପ୍ରୟୋଗ ସ୍ଥଗିତ ରଖିବାକୁ ପରାମର୍ଶ ଦିଆଯାଇଛି। କ୍ଷେତରେ ପାଣି ରଖନ୍ତୁ ଏବଂ ଖରିଫ ଫସଲରେ କୌଣସି କୀଟପତଙ୍ଗ ପାଇଁ ସର୍ଭେ କରନ୍ତୁ।",
   "crops_data": {
      "paddy": {
         "advisory": [
            "ପାଣିପାଗ କାରଣରୁ, ଶୀଥ୍ ରଟ୍ ଏବଂ ଶୀଥ୍ ବ୍ଲାଇଟ୍ ହେବାର ସମ୍ଭାବନା ରହିଛି। ଟେବୁକୋନାଜୋଲ 50 ପ୍ରତିଶତ + ଟ୍ରାଇଫ୍ଲୋକ୍ସିସ୍ଟ୍ରୋବିନ 25 ପ୍ରତିଶତ ଡବ୍ଲୁ. ଜି. କିମ୍ବା ପ୍ରୋପିକୋନାଜୋଲ 25 ପ୍ରତିଶତ ଇ. ସି. ସହିତ ପରିଚାଳନା କରନ୍ତୁ।"
         ]
      },
      "kharif pulses": {
         "advisory": [
            "ଇମାମେକ୍ଟିନ୍ ବେନ୍ଜୋଏଟ୍ 5 ପ୍ରତିଶତ ଏସ୍. ଜି., କ୍ଲୋରାଣ୍ଟ୍ରାନିଲିପ୍ରୋଲ୍ <ଆଇ. ଡି. 1> ଏସ୍. ସି., କିମ୍ବା ପ୍ରୋଫେନୋଫସ୍ 50 ପ୍ରତିଶତ ଇ. ସି. ସହିତ ପୋଡ୍ ବୋରର୍ ପରିଚାଳନା କରନ୍ତୁ।"
         ]
      },
      "ragi": {
         "advisory": [
            "ବିସ୍ଫୋରଣ ପାଇଁ ପରିସ୍ଥିତି ଅନୁକୂଳ ରହିଛି। ଟ୍ରାଇସାଇକ୍ଲାଜୋଲ 75 ପ୍ରତିଶତ ଡବ୍ଲ୍ଯ଼ୁ. ପି. ସହିତ ପରିଚାଳନା କରନ୍ତୁ।"
         ]
      },
      "sesamum": {
         "advisory": [
            "ପତଳା କରିବା କାର୍ଯ୍ଯ଼ କରନ୍ତୁ ଏବଂ ସର୍ବୋତ୍ତମ ଉଦ୍ଭିଦ ସଂଖ୍ଯ଼ା ବଜାଯ଼ ରଖନ୍ତୁ |"
         ]
      },
      "maize": {
         "advisory": [
            "ମକା ରେ ଏଫିଡ୍ ର ସମ୍ଭାବନା, ଡାଇମେଥୋଏଟ୍ ସହିତ ପରିଚାଳନା କରନ୍ତୁ |"
         ]
      },
      "groundnut": {
         "advisory": [
            "ରୁଟ୍ ରଟ୍ ରୋଗ ଦେଖିବାକୁ ମିଳିଛି, କାର୍ବେନଡାଜିମ୍ ସହିତ ପରିଚାଳନା କରନ୍ତୁ |"
         ]
      },
      "ginger": {
         "advisory": [
            "ରାଇଜୋମ କ୍ଷଯ଼ ଦେଖାଯାଇପାରେ, ଉପଶମକାରୀ ପଦକ୍ଷେପ ଭାବରେ ଟାଗମାଇସିନ୍ ଏବଂ ନିମ୍ବ ତେଲ ପ୍ରଯ଼ୋଗ କରନ୍ତୁ |"
         ]
      },
      "vegetables": {
         "advisory": [
            "ନର୍ସରୀରେ ଶୀତକାଳୀନ ପନିପରିବା ଚାଷ ଏବଂ ରୋପଣ, ଖରିଫ ପନିପରିବା ଯତ୍ନ ଏବଂ ରକ୍ଷଣାବେକ୍ଷଣ, ଏବଂ ଅମଳ ପରବର୍ତ୍ତୀ ପ୍ରଯୁକ୍ତି।"
         ]
      },
      "cucurbits": {
         "advisory": [
            "ଡାଉନି ମାଇଲ୍ଡ୍ଯ଼ୁ ରୋଗର ସମ୍ଭାବନା, କପର୍ ହାଇଡ୍ରୋକ୍ସାଇଡ୍ 77% ଡବ୍ଲ୍ଯ଼ୁ. ପି. ସହିତ ପରିଚାଳନା କରନ୍ତୁ।"
         ]
      },
      "flowers": {
         "advisory": [
            "ନର୍ସରୀରେ ଋତୁକାଳୀନ ଏବଂ ଶୀତକାଳୀନ ଫୁଲ ଲଗାଇବା, ଚାରା ଲଗାଇବା, କଲମ ଲଗାଇବା ଏବଂ ମଞ୍ଜି ବୁଣିବା।"
         ]
      },
      "pisciculture": {
         "advisory": [
            "ବର୍ଷା ଜଳ ଦ୍ୱାରା ହେଉଥିବା ଅମ୍ଳତା ପ୍ରଭାବକୁ ହ୍ରାସ କରିବା ପାଇଁ ଚୂନ ଲଗାନ୍ତୁ।"
         ]
      }
   },
   "date": "20-09-2024"
}